napari_psf_simulator/__init__.py
napari_psf_simulator/_calculator_widget.py
napari_psf_simulator/_contrast_widget.py
napari_psf_simulator/_version.py
napari_psf_simulator/_widget.py
napari_psf_simulator/napari.yaml
napari_psf_simulator/_tests/__init__.py
napari_psf_simulator/_tests/test_widget.py
napari_psf_simulator/auxiliary_handlers/PyFocus_auxiliary_handler.py
napari_psf_simulator/psf_submodules/__init__.py
napari_psf_simulator/psf_submodules/aberrations.py
napari_psf_simulator/psf_submodules/gui_utils.py
napari_psf_simulator/psf_submodules/normalize_intensity.py
napari_psf_simulator/psf_submodules/psf_generator.py
napari_psf_simulator/psf_submodules/sim_pupil.py
napari_psf_simulator/psf_submodules/subsection.py
napari_psf_simulator/psf_submodules/switchable_layout.py
napari_psf_simulator/psf_submodules/zernike_polynomials.py
napari_psf_simulator/psf_submodules/old/_aberrations.py
napari_psf_simulator/psf_submodules/old/_gui_utils.py
napari_psf_simulator-0.3.1.dist-info/LICENSE
napari_psf_simulator-0.3.1.dist-info/METADATA
napari_psf_simulator-0.3.1.dist-info/WHEEL
napari_psf_simulator-0.3.1.dist-info/entry_points.txt
napari_psf_simulator-0.3.1.dist-info/top_level.txt
napari_psf_simulator-0.3.1.dist-info/RECORD
