Metadata-Version: 2.1
Name: napari-psf-simulator
Version: 0.3.1
Summary: A plugin for simulations of the Point Spread Function, with aberrations
Home-page: https://github.com/andreabassi78/napari-psf-simulator
Author: Andrea Bassi
Author-email: andrea1.bassi@polimi.it
License: BSD-3-Clause
Project-URL: Bug Tracker, https://github.com/andreabassi78/napari-psf-simulator/issues
Project-URL: Documentation, https://github.com/andreabassi78/napari-psf-simulator#README.md
Project-URL: Source Code, https://github.com/andreabassi78/napari-psf-simulator
Project-URL: User Support, https://github.com/andreabassi78/napari-psf-simulator/issues
Classifier: Development Status :: 2 - Pre-Alpha
Classifier: Intended Audience :: Developers
Classifier: Framework :: napari
Classifier: Topic :: Software Development :: Testing
Classifier: Programming Language :: Python
Classifier: Programming Language :: Python :: 3
Classifier: Programming Language :: Python :: 3.8
Classifier: Programming Language :: Python :: 3.9
Classifier: Programming Language :: Python :: 3.10
Classifier: Operating System :: OS Independent
Classifier: License :: OSI Approved :: BSD License
Requires-Python: >=3.8
License-File: LICENSE
Requires-Dist: numpy
Requires-Dist: magicgui
Requires-Dist: qtpy
Requires-Dist: PyCustomFocus >=3.3.6
Requires-Dist: matplotlib
Requires-Dist: scikit-image
Requires-Dist: scipy
Provides-Extra: testing
Requires-Dist: tox ; extra == 'testing'
Requires-Dist: pytest ; extra == 'testing'
Requires-Dist: pytest-cov ; extra == 'testing'
Requires-Dist: qtpy ; extra == 'testing'
Requires-Dist: pytest-qt ; extra == 'testing'
Requires-Dist: napari ; extra == 'testing'
Requires-Dist: pyqt5 ; extra == 'testing'
Requires-Dist: PyCustomFocus >=3.3.6 ; extra == 'testing'
Requires-Dist: matplotlib ; extra == 'testing'
Requires-Dist: scikit-image ; extra == 'testing'
Requires-Dist: scipy ; extra == 'testing'
